simple_mongodb/__init__.py
simple_mongodb/base_collection.py
simple_mongodb/exceptions.py
simple_mongodb/index.py
simple_mongodb/mongodb_client.py
simple_mongodb/py.typed
simple_mongodb-0.9.0.dist-info/licenses/LICENSE
simple_mongodb-0.9.0.dist-info/METADATA
simple_mongodb-0.9.0.dist-info/WHEEL
simple_mongodb-0.9.0.dist-info/top_level.txt
simple_mongodb-0.9.0.dist-info/RECORD
