Metadata-Version: 2.4
Name: simple-mongodb
Version: 0.9.0
Summary:  An asynchronous Python package for streamlined collection management in MongoDB 
License: MIT License
Project-URL: Homepage, https://github.com/Gandori/Simple-MongoDB
Project-URL: Documentation, https://github.com/Gandori/Simple-MongoDB
Project-URL: Repository, https://github.com/Gandori/Simple-MongoDB
Project-URL: Changelog, https://github.com/Gandori/Simple-MongoDB/blob/master/CHANGELOG.md
Classifier: Programming Language :: Python
Classifier: Programming Language :: Python :: 3.12
Classifier: Intended Audience :: Developers
Classifier: Topic :: Database
Requires-Python: >=3.12
License-File: LICENSE
Requires-Dist: motor==3.5.0
Requires-Dist: pymongo==4.8.0
Provides-Extra: dev
Requires-Dist: isort==5.13.2; extra == "dev"
Requires-Dist: black==24.4.2; extra == "dev"
Requires-Dist: pytest==8.2.2; extra == "dev"
Requires-Dist: pytest-asyncio==0.23.7; extra == "dev"
Requires-Dist: fakeredis==2.23.2; extra == "dev"
Requires-Dist: pytest-mock==3.14.0; extra == "dev"
Requires-Dist: pytest-sugar==1.0.0; extra == "dev"
Requires-Dist: toml==0.10.2; extra == "dev"
Requires-Dist: setuptools==74.1.2; extra == "dev"
Requires-Dist: wheel==0.44.0; extra == "dev"
Requires-Dist: build==1.2.2; extra == "dev"
Requires-Dist: twine==6.1.0; extra == "dev"
Dynamic: license-file
